[
  {
    "id": 21681984,
    "date": "2026-04-26",
    "season": 2025,
    "status": "2026-04-26T17:00:00Z",
    "period": 0,
    "time": null,
    "postseason": true,
    "postponed": false,
    "home_team_score": 0,
    "visitor_team_score": 0,
    "datetime": "2026-04-26T17:00:00.000Z",
    "home_q1": null,
    "home_q2": null,
    "home_q3": null,
    "home_q4": null,
    "home_ot1": null,
    "home_ot2": null,
    "home_ot3": null,
    "home_timeouts_remaining": null,
    "home_in_bonus": null,
    "visitor_q1": null,
    "visitor_q2": null,
    "visitor_q3": null,
    "visitor_q4": null,
    "visitor_ot1": null,
    "visitor_ot2": null,
    "visitor_ot3": null,
    "visitor_timeouts_remaining": null,
    "visitor_in_bonus": null,
    "ist_stage": null,
    "home_team": {
      "id": 28,
      "conference": "East",
      "division": "Atlantic",
      "city": "Toronto",
      "name": "Raptors",
      "full_name": "Toronto Raptors",
      "abbreviation": "TOR"
    },
    "visitor_team": {
      "id": 6,
      "conference": "East",
      "division": "Central",
      "city": "Cleveland",
      "name": "Cavaliers",
      "full_name": "Cleveland Cavaliers",
      "abbreviation": "CLE"
    }
  },
  {
    "id": 21681985,
    "date": "2026-04-26",
    "season": 2025,
    "status": "2026-04-26T19:30:00Z",
    "period": 0,
    "time": null,
    "postseason": true,
    "postponed": false,
    "home_team_score": 0,
    "visitor_team_score": 0,
    "datetime": "2026-04-26T19:30:00.000Z",
    "home_q1": null,
    "home_q2": null,
    "home_q3": null,
    "home_q4": null,
    "home_ot1": null,
    "home_ot2": null,
    "home_ot3": null,
    "home_timeouts_remaining": null,
    "home_in_bonus": null,
    "visitor_q1": null,
    "visitor_q2": null,
    "visitor_q3": null,
    "visitor_q4": null,
    "visitor_ot1": null,
    "visitor_ot2": null,
    "visitor_ot3": null,
    "visitor_timeouts_remaining": null,
    "visitor_in_bonus": null,
    "ist_stage": null,
    "home_team": {
      "id": 25,
      "conference": "West",
      "division": "Northwest",
      "city": "Portland",
      "name": "Trail Blazers",
      "full_name": "Portland Trail Blazers",
      "abbreviation": "POR"
    },
    "visitor_team": {
      "id": 27,
      "conference": "West",
      "division": "Southwest",
      "city": "San Antonio",
      "name": "Spurs",
      "full_name": "San Antonio Spurs",
      "abbreviation": "SAS"
    }
  },
  {
    "id": 21681986,
    "date": "2026-04-26",
    "season": 2025,
    "status": "2026-04-27T01:30:00Z",
    "period": 0,
    "time": null,
    "postseason": true,
    "postponed": false,
    "home_team_score": 0,
    "visitor_team_score": 0,
    "datetime": "2026-04-27T01:30:00.000Z",
    "home_q1": null,
    "home_q2": null,
    "home_q3": null,
    "home_q4": null,
    "home_ot1": null,
    "home_ot2": null,
    "home_ot3": null,
    "home_timeouts_remaining": null,
    "home_in_bonus": null,
    "visitor_q1": null,
    "visitor_q2": null,
    "visitor_q3": null,
    "visitor_q4": null,
    "visitor_ot1": null,
    "visitor_ot2": null,
    "visitor_ot3": null,
    "visitor_timeouts_remaining": null,
    "visitor_in_bonus": null,
    "ist_stage": null,
    "home_team": {
      "id": 11,
      "conference": "West",
      "division": "Southwest",
      "city": "Houston",
      "name": "Rockets",
      "full_name": "Houston Rockets",
      "abbreviation": "HOU"
    },
    "visitor_team": {
      "id": 14,
      "conference": "West",
      "division": "Pacific",
      "city": "Los Angeles",
      "name": "Lakers",
      "full_name": "Los Angeles Lakers",
      "abbreviation": "LAL"
    }
  },
  {
    "id": 21682727,
    "date": "2026-04-26",
    "season": 2025,
    "status": "2026-04-26T23:00:00Z",
    "period": 0,
    "time": null,
    "postseason": true,
    "postponed": false,
    "home_team_score": 0,
    "visitor_team_score": 0,
    "datetime": "2026-04-26T23:00:00.000Z",
    "home_q1": null,
    "home_q2": null,
    "home_q3": null,
    "home_q4": null,
    "home_ot1": null,
    "home_ot2": null,
    "home_ot3": null,
    "home_timeouts_remaining": null,
    "home_in_bonus": null,
    "visitor_q1": null,
    "visitor_q2": null,
    "visitor_q3": null,
    "visitor_q4": null,
    "visitor_ot1": null,
    "visitor_ot2": null,
    "visitor_ot3": null,
    "visitor_timeouts_remaining": null,
    "visitor_in_bonus": null,
    "ist_stage": null,
    "home_team": {
      "id": 23,
      "conference": "East",
      "division": "Atlantic",
      "city": "Philadelphia",
      "name": "76ers",
      "full_name": "Philadelphia 76ers",
      "abbreviation": "PHI"
    },
    "visitor_team": {
      "id": 2,
      "conference": "East",
      "division": "Atlantic",
      "city": "Boston",
      "name": "Celtics",
      "full_name": "Boston Celtics",
      "abbreviation": "BOS"
    }
  }
]